vcdextmessageworker/__init__.py
vcdextmessageworker/message_worker.py
VcdExtMessageWorker-0.3.dist-info/METADATA
VcdExtMessageWorker-0.3.dist-info/WHEEL
VcdExtMessageWorker-0.3.dist-info/top_level.txt
VcdExtMessageWorker-0.3.dist-info/RECORD
