Metadata-Version: 2.1
Name: VcdExtMessageWorker
Version: 0.3
Summary: RabbitMQ message worker for vCloud Director Extensibility SDK
Home-page: https://github.com/lrivallain/VcdExtMessageWorker
Author: Ludovic Rivallain
Author-email: ludovic.rivallain@gmail.com
License: MIT
Platform: UNKNOWN
Classifier: Programming Language :: Python :: 3
Classifier: License :: OSI Approved :: MIT License
Classifier: Operating System :: OS Independent
Requires-Dist: kombu
